{
  "doc_id": "executive-order-no-275-s-2000",
  "category": "executive_order",
  "category_slug": "executive-orders",
  "president_slug": "joseph-ejercito-estrada",
  "date": "2000-08-30",
  "title": "Executive Order No. 275, s. 2000",
  "content_url": "https://www.officialgazette.gov.ph/2000/08/30/executive-order-no-275-s-2000/",
  "pdf_url": "https://www.officialgazette.gov.ph/downloads/2000/08aug/20000830-EO-0275-JEE.pdf",
  "text": "MALACAÑANG MANILA\n\nEXECUTIVE ORDER NO. 275\n\nDIRECTING THE COMMITTEE ON SCIENTIFIC AND TECHNICAL COOPERATION WITH SOCIALIST COUNTRIES TO DELETE THE SOCIALIST REPUBLIC OF VIETNAM FROM THE LIST OF COUNTRIES COVERED BY LETTER OF INSTRUCTIONS NO. 444\n\nWHEREAS, Letter of Instructions No. 444 dated 9 August 1976 has included the Socialist Republic of Vietnam in the list of socialist countries and other centrally-planned countries;\n\nWHEREAS , the Socialist Republic of Vietnam has started to move towards an open economy and is committed to liberalize its markets and integrate into the global market economy;\n\nWHEREAS , the Socialist Republic of Vietnam is now a member of the Association of Southeast Asian Nations (ASEAN) and the Asia-Pacific Economic Cooperation (APEC), and is in the process of accession to the World Trade Organization;\n\nWHEREAS , it is the policy of the Government to develop and strengthen trade relations with the Socialist Republic of Vietnam;\n\nWHEREAS , a continued coverage of the Socialist Republic of Vietnam by Letter of Instructions 444 is no longer consistent with the country’s national interest, as coursing trade between our countries through the Philippine International Trading Corporation is becoming an unnecessary barrier to trade.\n\nNOW, THEREFORE, I, JOSEPH EJERCITO ESTRADA , President of the Republic of the Philippines, by virtue of the powers vested in me by law, do hereby order:\n\nThe Committee on Scientific and Technical Cooperation with Socialist Countries to remove the Socialist Republic of Vietnam from the list of countries covered by Letter of Instructions No. 444.\n\nDONE in the City of Manila, this 30th day of August, in the Year of Our Lord, Two Thousand.\n\n(Sgd.) JOSEPH EJERCITO ESTRADA President of the Philippines\n\nBy the President:\n\n(Sgd.) RONALDO B. ZAMORA Executive Secretary\n\nSource : Presidential Management Staff\n\nOffice of the President of the Philippines. (2000). [Executive Order Nos. : 1 – 338]. Manila : Presidential Management Staff.",
  "word_count": 311,
  "has_html_content": true,
  "is_pdf_only": false,
  "scrape_status": "success",
  "scrape_error": null,
  "scraped_at": "2026-02-23T09:22:35.340717Z"
}