{
  "doc_id": "proclamation-no-99-s-1992",
  "category": "proclamation",
  "category_slug": "proclamations",
  "president_slug": "fidel-v-ramos",
  "date": "1992-11-23",
  "title": "Proclamation No. 99, s. 1992",
  "content_url": "https://www.officialgazette.gov.ph/1992/11/23/proclamation-no-99-s-1992/",
  "pdf_url": "https://www.officialgazette.gov.ph/downloads/1992/11nov/19921123-PROC-0099-FVR.pdf",
  "text": "MALACAÑANG Manila\n\nPROCLAMATION NO. 99\n\nAMENDING PROCLAMATION NO. 56, DATED SEPTEMBER 22, 1992, WHICH DECLARED SEPTEMBER 25-30, 1992, AND EVERY YEAR THEREAFTER AS THE LINGGO NG KABATAAN IN THE PHILIPPINES\n\nBy virtue of the powers vested in me by law, I, FIDEL V. RAMOS, President of the Philippines, do hereby amend Proclamation No. 56, dated September 22, 1992, which declared the period from September 25 to 30, 1992, and every year thereafter as Linggo ng Kabataan in the Philippines by transferring the celebration of Linggo ng Kabataan to the second week of December of every year.\n\nIN WITNESS WHEREOF, I have hereunto set my hand and caused the seal of the Republic of the Philippines to be affixed.\n\nDone in the City of Manila, this 23rd day of November, in the year of Our Lord, nineteen hundred and ninety two.\n\n(Sgd.) FIDEL V. RAMOS\n\nBy the President: (Sgd.) EDELMIRO A. AMANTE, SR. Executive Secretary\n\nSource: CDAsia",
  "word_count": 156,
  "has_html_content": true,
  "is_pdf_only": false,
  "scrape_status": "success",
  "scrape_error": null,
  "scraped_at": "2026-02-23T15:58:25.401329Z"
}