{
  "doc_id": "executive-order-no-290-s-1940",
  "category": "executive_order",
  "category_slug": "executive-orders",
  "president_slug": "manuel-l-quezon",
  "date": "1940-07-08",
  "title": "Executive Order No. 290, s. 1940",
  "content_url": "https://www.officialgazette.gov.ph/1940/07/08/executive-order-no-290-s-1940/",
  "pdf_url": "https://www.officialgazette.gov.ph/downloads/1940/07jul/19400708-EO-0290-MLQ.pdf",
  "text": "MALACAÑAN PALACE MANILA\n\nEXECUTIVE ORDER NO. 290\n\nPROMULGATING RULES AND REGULATIONS GOVERNING THE GIVING OF SECURITY FOR EVERY FIREARM HELD UNDER THE PROVISIONS OF SECTION 888 OF THE REVISED ADMINISTRATIVE CODE\n\nPursuant to the authority vested in me under section nine hundred and five of the Revised Administrative Code, I, Manuel L. Quezon, President of the Philippines, do hereby issue the following rules and regulations to govern the giving of security for every firearm held on license issued under the provisions of section eight hundred and eighty-eight of the same code:\n\n1. Any person desiring to possess one or more firearms for personal protection or for use in hunting or other lawful purposes and ammunition thereof shall, upon making application therefor and before receiving the license, for the purpose of security, deposit a United States or Philippine Government bond or make a cash deposit with the Postal Savings Bank in the sum of forty pesos for each firearm for which the license is to be issued and indorse the certificate of deposit therefor to the Treasurer of the Philippines, such deposit to bear no interest; or give a personal or property bond signed by two (2) persons or by a surety company in such form as the President may prescribe, payable to the Government of the Philippines, in the sum of one hundred pesos for each such firearms.\n\n2. The bonds existing upon the promulgation of this exec­utive order shall continue as they are or, at the option of the interested party, the same can be renewed in accordance with the provisions hereof.\n\n3. Gun clubs duly organized and accredited by the Chief of Constabulary may be allowed to possess on licenses, for the use of its members at the clubs, not to exceed twenty (20) firearms (rifles, pistols, revolvers, or shotguns). The club shall, for the purpose of security, give one-half (½) of the total amount of the security herein required for firearms issued to nonmembers of gun clubs. In case of loss, the sum of forty pesos or one hundred pesos, as the case may be, shall be forfeited or collected for each firearm lost.\n\nDone at the City of Manila, this 8th day of July, in the year of Our Lord, nineteen hundred and forty, and of the Commonwealth of the Philippines, the fifth.\n\n(Sgd.) MANUEL L. QUEZON President of the Philippines\n\nBy the President:\n\n(Sgd.) JORGE B. VARGAS Secretary to the President\n\nSource: Presidential Museum and Library\n\nOffice of the President of the Philippines. (1940). [Executive Order Nos. : 335 – 400]. Manila : Presidential Museum and Library.",
  "word_count": 432,
  "has_html_content": true,
  "is_pdf_only": false,
  "scrape_status": "success",
  "scrape_error": null,
  "scraped_at": "2026-02-23T09:30:57.623340Z"
}