{
  "doc_id": "executive-order-no-59-s-1936",
  "category": "executive_order",
  "category_slug": "executive-orders",
  "president_slug": "manuel-l-quezon",
  "date": "1936-10-21",
  "title": "Executive Order No. 59, s. 1936",
  "content_url": "https://www.officialgazette.gov.ph/1936/10/21/executive-order-no-59-s-1936/",
  "pdf_url": "https://www.officialgazette.gov.ph/downloads/1936/10oct/19361021-EO-0059-MLQ.pdf",
  "text": "MALACAÑAN PALACE MANILA\n\nEXECUTIVE ORDER NO. 59\n\nTRANSFERRING THE SEAT OF GOVERNMENT OF THE MUNICIPAL DISTRICT OF KABASALAN, ZAMBOANGA, FROM ITS PRESENT LOCATION AT THE BARRIO OF NAGA TO THE BARRIO OF KABASALAN\n\nUpon the recommendation of the provincial board of Zamboanga, concurred in by the Director of the Bureau of non-Christian Tribes and the Honorable, the Secretary of the Interior, and pursuant to the provisions of section sixty-eight of the Revised Administrative Code, the seat of government of the Municipal District of Kabasalan, Province of Zamboanga, as organized under Executive Order Numbered One hundred thirty-five, series of nineteen hundred and twenty-eight, of the Governor-General, is hereby transferred from its present location at Naga to the Barrio of Kabasalan, said municipal district.\n\nThe transfer herein made shall take effect on November fifteenth, nineteen hundred and thirty-six.\n\nDone at the City of Manila, this twenty-first day of October, in the year of Our Lord, nineteen hundred and thirty-six, and of the Commonwealth of the Philippines, the first.\n\nMANUEL L. QUEZON President of the Philippines\n\nBy the President:\n\nELPIDIO QUIRINO Secretary of the Interior\n\nSource : Presidential Museum and Library\n\nBureau of Printing. (1938). Executive Order No. 59. Messages of the President, 2 (1), pp. 875.",
  "word_count": 204,
  "has_html_content": true,
  "is_pdf_only": false,
  "scrape_status": "success",
  "scrape_error": null,
  "scraped_at": "2026-02-23T09:25:19.594127Z"
}