{
  "doc_id": "administrative-order-no-91-s-1939",
  "category": "administrative_order",
  "category_slug": "administrative-orders",
  "president_slug": "manuel-l-quezon",
  "date": "1939-04-18",
  "title": "Administrative Order No. 91, s. 1939",
  "content_url": "https://www.officialgazette.gov.ph/1939/04/18/administrative-order-no-91-s-1939/",
  "pdf_url": "https://www.officialgazette.gov.ph/downloads/1939/04apr/19390418-AO-0091-MLQ.pdf",
  "text": "MALACAÑAN PALACE MANILA\n\nADMINISTRATIVE ORDER NO. 91\n\nDISMISSING JUSTICE OF THE PEACE MARCELO G. RAMOS OF LAS PIÑAS, RIZAL, AND DISQUALIFYING HIM FROM HOLDING PUBLIC OFFICE.\n\nThis is an administrative case filed by the law firm of Feria and La O against Marcelo G. Ramos, justice of the peace of the municipality of Las Piñas, Province of Rizal.\n\nIt is alleged in the complaint that the respondent required one Francisco Uy, who figured in a certain automobile accident, to file a bond of two hundred pesos for the latter’s temporary release, and that thereafter when the case had already been settled amicably between the parties, he failed to return the said amount when required to do so by Francisco Uy, and only after repeated extensions of time given him to make payment was the respondent able to return the amount of one hundred fifty pesos in instalments, there being still due from the respondent the sum of fifty pesos. During the investigation conducted by the District Judge of Rizal the respondent admitted having received the sum of two hundred pesos, not in the form of a bond, however, but as a simple loan obtained from Francisco Uy sometime after the amicable settlement of the latter’s case.\n\nAfter a careful review of the record of this case, I am fully in accord with the conclusion of the District Judge to the effect that the respondent really exacted the sum of two hundred pesos from Francisco Uy as bond for the latter’s provisional release and that thereafter he misappropriated said amount. The documentary evidence squarely corroborates the testimony of the complainant. In the receipt issued by Francisco Uy on May twenty-fifth, nineteen hundred and thirty-eight, which is countersigned by the respondent, it is stated that the sum of one hundred pesos was received from the respondent as “part payment of the two hundred pesos deposited with him.” Moreover in a letter dated July eleventh, nineteen hundred and thirty-eight, written by the respondent to the lawyer of Francisco Uy asking said attorney to intercede in his behalf so that he might obtain another period of grace within which to make good his obligation, the respondent gave Francisco Uy “the option to prosecute him” should he fail to pay the balance due on the date promised by him. Even conceding for the sake of argument, the defense of the respondent that he borrowed the sum of two hundred pesos from Francisco Uy, whom he scarcely knew, through the intervention of a China man whose name he does not even remember, the respondent stands convicted, by his own admission, of extorting a loan from a prospective party litigant before his court. Such conduct is highly censurable, to say the least, and is in my opinion alone sufficient to cause his removal from the service.\n\nIt also appears of record that there is pending trial in the Court of First Instance of Rizal an information filed by the provincial fiscal against the respondent for the crime of estafa in that the respondent is alleged to have misappropriated a cash bond of one thousand two hundred pesos for the temporary release of a China man accused in his court of violation of the Opium Law.\n\nI announced my firm determination at the inception of my administration to weed the judiciary of undesirables to the end that the standard of the bench might be raised to the highest level both intellectually and morally. The respondent has by his conduct shown that he is grossly unfit to hold any position of trust and responsibility and his continuance in office will seriously undermine public confidence in our courts of justice.\n\nIn view of the foregoing, and concurring in the recommendation of the Secretary of Justice, I, Manuel L. Quezon, President of the Philippines, do hereby dismiss Marcelo G. Ramos as justice of the peace of Las Piñas, Rizal, and disqualify him forever from holding public office.\n\nDone at the City of Manila, this eighteenth day of April, in the year of Our Lord, nineteen hundred and thirty-nine, and of the Commonwealth of the Philippines, the fourth.\n\nMANUEL L. QUEZON President of the Philippines\n\nBY THE PRESIDENT:\n\nJORGE B. VARGAS Secretary to the President\n\nSource: Presidential Museum and Library\n\nBureau of Printing. (1941). Administrative Order No. 91. Messages of the President, 5 (1), 1303-1304.",
  "word_count": 723,
  "has_html_content": true,
  "is_pdf_only": false,
  "scrape_status": "success",
  "scrape_error": null,
  "scraped_at": "2026-02-23T04:27:24.899970Z"
}