{
  "doc_id": "memorandum-order-no-794-s-1983",
  "category": "memorandum_order",
  "category_slug": "memorandum-orders",
  "president_slug": "ferdinand-e-marcos",
  "date": "1983-09-19",
  "title": "Memorandum Order No. 794, s. 1983",
  "content_url": "https://www.officialgazette.gov.ph/1983/09/19/memorandum-order-no-794-s-1983/",
  "pdf_url": "https://www.officialgazette.gov.ph/downloads/1983/09sep/19830919-MO-0794-FM.pdf",
  "text": "Office of the President of the Philippines Malacañang\n\nMEMORANDUM ORDER NO. 794\n\nTo: All Officials and Employees Office of the President –\n\nIt has come to my attention that more than fifty percent (50%) of the work force of this Office left their posts before the official departure time on August 22, 1983, in violation of civil service rules and regulations on attendance. In some instances official transactions virtually ceased in a number of offices or units as employees left long before the prescribed dismissal time. Some employees left on their own volition without even bothering to ask permission from their supervisors or unit heads. Their irresponsible acts nearly paralyzed the services on such flimsy excuses as alleged lack of public transportation, brownouts, imagined fears of rallies, illness, family problems and other concocted alibis.\n\nIt should be borne in mind that the authorities concerned are well aware of the prevailing peace and order situation on the aforementioned date and are cognizant of the employees’ safety and welfare.\n\nIt is, therefore, directed that, henceforth, all officials and employees in this Office, under similar circumstances as those obtaining on August 21, 1983, should remain in their offices until the prescribed departure time or until office hours are officially suspended.\n\nHeads of offices or primary units, may, however, continue to exercise their discretion to allow their employees, on a case to case basis, to leave their posts before dismissal time for valid and justifiable reasons. But in no case shall they be allowed to leave their posts, en masse, without prior permission from the undersigned.\n\nStrict compliance with this Order is enjoined and violation thereof will be dealt with more drastically in the future.\n\n(Sgd.) JUAN C. TUVERA Presidential Executive Assistant\n\nManila, September 19, 1983\n\nSource: Presidential Management Staff Library",
  "word_count": 297,
  "has_html_content": true,
  "is_pdf_only": false,
  "scrape_status": "success",
  "scrape_error": null,
  "scraped_at": "2026-02-23T12:04:50.103390Z"
}