{
  "doc_id": "proclamation-no-1356-s-2007",
  "category": "proclamation",
  "category_slug": "proclamations",
  "president_slug": "gloria-macapagal-arroyo",
  "date": "2007-08-13",
  "title": "Proclamation No. 1356, s. 2007",
  "content_url": "https://www.officialgazette.gov.ph/2007/08/13/proclamation-no-1356-s-2007/",
  "pdf_url": "https://www.officialgazette.gov.ph/downloads/2007/08aug/20070813-PROC-1356-GMA.pdf",
  "text": "MALACAÑANG Manila\n\nPROCLAMATION NO. 1356\n\nAMENDING PROCLAMATION NO. 1187 DATED MARCH 27, 1998, GRANTING OWNERSHIP TO THE NATIONAL POLICE COMMISSION (NAPOLCOM) OF THE LAND DESCRIBED IN PROCLAMATION NO. 1453 DATED JUNE 30, 1975, BY AUTHORIZING THE BASES CONVERSION DEVELOPMENT AUTHORITY (BCDA) TO ADMINISTER AND DEVELOP FOR THE BENEFIT OF THE NAPOLCOM THE SAID LAND AND THOSE PROPERTIES CONVEYED BY BCDA\n\nWHEREAS , Proclamation No. 1453 dated June 30, 1975, reserved a parcel of land with an area of 87,389 sq. m. located in Fort Bonifacio for the site of the National Police Commission hereinafter referred as “Property”, and provided that the same will automatically revert to military control when no longer needed for that purpose;\n\nWHEREAS , Proclamation No. 1187 dated March 27, 1998 vested ownership of the Property upon the National Police Commission to which was issued Special Patent No. 3617 on December 14, 2004 by the Land Management Bureau and Original Certificate of Title No. SP8047 on June 10, 2005 issued by the Register of Deeds of Makati City;\n\nWHEREAS , on September 8, 2004, the BCDA and the NAPOLCOM entered into a Memorandum of Agreement to implement a swap of properties in Fort Bonifacio, with the BCDA conveying and transferring to the NAPOLCOM a total land area of approximately Thirteen Thousand Seven Hundred Thirty One and Seventeen (13,731.17) square meters without land use restriction covered by Transfer Certificates of Titles and a total of Two Thousand Two Hundred Fifty (2,250) housing units in the Pamayanang Diego Silang Village, Fort Bonifacio, Taguig City, while the NAPOLCOM conveyed and transferred to the BCDA a total land area of approximately Thirty Thousand One Hundred Twenty (30,120) square meters located at Fort Bonifacio, Taguig City and approximately Twenty Thousand (20,000) square meters located at Camp Bago Bantay, Quezon City;\n\nWHEREAS , Proclamation No. 1187 was amended by Proclamation No. 1144 on September 20, 2006 which transferred to the BCDA the administration and ownership as well as the disposal through lease or sale of the area conveyed by the NAPOLCOM. However, neither Proclamation No. 1187 nor Proclamation No. 1144 lift the restriction on the use of the site;\n\nWHEREAS , in view of the swap of properties, the NAPOLCOM retained an area of Fifty Seven Thousand Two Hundred Sixty Nine (57,269) square meters of land at Fort Bonifacio, Taguig City which is still subject to use restrictions and an additional Thirteen Thousand Seven Hundred Thirty One and Seventeen (13,731.17) square meters for a total of Seventy One Thousand and Seventeen (71,000.17) square meters, described as follows:\n\na. A PARCEL OF LAND (Lot 6 of the subdivision plan Psd-00-068987, being a portion of Swo-007602-001100-D, Land SWAP, LRC Record No. ), situated in Barangay Fort Bonifacio, Makati City, Metro Manila, Island of Luzon. b. Transfer Certificate of Title No. 36259 c. Transfer Certificate of Title No. 36260 d. Transfer Certificate of Title No. 36208 e. Transfer Certificate of Title No. 36209 f. Transfer Certificate of Title No. 36211 g. Transfer Certificate of Title No. 36212 h. Transfer Certificate of Title No. 36213 i . Transfer Certificate of Title No. 36214 j. Transfer Certificate of Title No. 36215 k. Transfer Certificate of Title No. 36216 l. Transfer Certificate of Title No. 36217 m. Transfer Certificate of Title No. 36218 n. Transfer Certificate of Title No. 36262\n\nWHEREAS , it is to the best interest of the NAPOLCOM and the BCDA that the Property be developed and integrated into the Bonifacio Global City vision of a seamless and world class development. Its integration will have a direct and significant impact on the value of the Property and viability of any project that will be undertaken by the BCDA;\n\nWHEREAS , there is a great need for office buildings for NAPOLCOM, DILG and its attached agencies and housing units for deserving and qualified NAPOLCOM and if feasible, DILG and its attached agencies’ employees;\n\nWHEREAS , to pursue the abovementioned development, there is a need to authorize the BCDA to administer and develop the Property subject to NAPOLCOM specifications in accordance with the vision and concept of Bonifacio Global City;\n\nNOW, THEREFORE, I, GLORIA MACAPAGAL-ARROYO , President of the Republic of the Philippines, by virtue of the powers vested in me by law, do hereby order:\n\nSECTION 1. U se Restriction.\n\na. The following phrase under Proclamation No. 1453 dated June 30, 1975 is hereby repealed and revoked:\n\n“ x x x and to the condition that the area shall automatically revert to military control when no longer needed for the purpose stated x x x”\n\nb. The third paragraph of Proclamation No. 1187 dated March 27, 1998 is hereby amended to read as follows:\n\n“The land may be used as the site for the National Police Commission or, in the latter’s discretion, it may be devoted to any purpose whatsoever or disposed of in any manner consistent with law. Any use restriction upon the land shall immediately be removed or lifted upon the disposition of the land or any part thereof by the Commission to third parties.”\n\nSECTION 2. Disposal of the Property.\n\nIn view of the need of NAPOLCOM and DILG for office buildings and housing units for deserving and qualified NAPOLCOM employees, and DILG employees if feasible, the BCDA is hereby authorized to administer and develop the property of NAPOLCOM, subject to NAPOLCOM specifications to ensure that the desired development is realized and in accordance with the vision and concept of Bonifacio Global City.\n\nSECTION 3. This Proclamation shall take effect immediately.\n\nDone in the City of Manila this 13th day of August in the year of Our Lord Two Thousand and Seven.\n\n( Sgd .) GLORIA MACAPAGAL-ARROYO\n\nBy the President: ( Sgd .) EDUARDO R. ERMITA Executive Secretary\n\nSource: CDAsia",
  "word_count": 956,
  "has_html_content": true,
  "is_pdf_only": false,
  "scrape_status": "success",
  "scrape_error": null,
  "scraped_at": "2026-02-23T17:00:46.962269Z"
}