{
  "doc_id": "proclamation-no-1700-s-1978",
  "category": "proclamation",
  "category_slug": "proclamations",
  "president_slug": "ferdinand-e-marcos",
  "date": "1978-01-06",
  "title": "Proclamation No. 1700, s. 1978",
  "content_url": "https://www.officialgazette.gov.ph/1978/01/06/proclamation-no-1700-s-1978/",
  "pdf_url": "https://www.officialgazette.gov.ph/downloads/1978/01jan/19780106-PROC-1700-FM.pdf",
  "text": "MALACAÑANG Manila\n\nPROCLAMATION NO. 1700\n\nDECLARING MONDAY, JANUARY 9, 1978, AS A SPECIAL PUBLIC HOLIDAY IN DAGUPAN CITY\n\nWHEREAS, January 9, 1978, marks the historical landing of the American Forces led by the late Gen. Douglas MacArthur at Bonuan, Blue Beach, Dagupan City that ultimately led to the liberation of the Philippines from the Japanese Imperial Army; and\n\nWHEREAS, the residents of Dagupan City should be afforded the opportunity to commemorate this historical event with fitting ceremonies;\n\nNOW, THEREFORE, I, FERDINAND E. MARCOS, President of the Philippines, by virtue of the powers vested in me by law, do hereby declare Monday, January 9, 1978, as a special public holiday in Dagupan City.\n\nIN WITNESS WHEREOF, I have hereunto set my hand and caused the seal of the Republic of the Philippines to be affixed.\n\nDone in the City of Manila, this 6th day of January, in the year of Our Lord, nineteen hundred and seventy-eight.\n\n(SGD . )FERDINAND E. MARCOS President of the Philippines\n\nBy the President:\n\n(SGD.) JACOBO C. CLAVE Presidential Executive Assistant\n\nSource: CDAsia",
  "word_count": 176,
  "has_html_content": true,
  "is_pdf_only": false,
  "scrape_status": "success",
  "scrape_error": null,
  "scraped_at": "2026-02-23T15:06:21.557864Z"
}