{
  "doc_id": "proclamation-no-207-s-1967",
  "category": "proclamation",
  "category_slug": "proclamations",
  "president_slug": "ferdinand-e-marcos",
  "date": "1967-05-27",
  "title": "Proclamation No. 207, s. 1967",
  "content_url": "https://www.officialgazette.gov.ph/1967/05/27/proclamation-no-207-s-1967/",
  "pdf_url": "https://www.officialgazette.gov.ph/downloads/1967/05may/19670527-PROC-0207-FM.pdf",
  "text": "MALACAÑANG RESIDENCE OF THE PRESIDENT OF THE PHILIPPINES MANILA\n\nPROCLAMATION NO. 207\n\nRESERVING FOR NATIONAL SHRINE PURPOSES A CERTAIN PARCEL OF LAND OF THE PRIVATE DOMAIN SITUATED IN THE DISTRICT OF MALATE, CITY OF MANILA.\n\nUpon the recommendation of the Secretary of Agriculture and Natural Resources and pursuant to the authority vested in me by law, I, FERDINAND E. MARCOS, President of the Philippines, do hereby withdraw from sale or settlement and reserve for national shrine purposes under the administration of the National Shrines Commission, subject to private rights, if any there be, a certain parcel of land of the private domain, including all the improvements existing thereon, situated in the district of Malate, City of Manila, which is more particularly described as follows:\n\nFORT SAN ANTONIO ABAD\n\nA PARCEL OF LAND (the proposed Fort SAN ANTONIO ABAD NATIONAL SHRINE), situated in the District of Malate, City of Manila. Bounded on all sides, by Lot 1 of plan Swo-18580. Beginning at a point marked “1” on plan, being N. 47 deg. 15’W., 477.02 m. from C.B.M. 2, City of Manila,\n\nthence N. 23 deg. 50′ W., 46.00 m. to point at 2;\n\nthence S. 68 deg. 00′ W., 7.00 m. to point 3;\n\nthence N. 23 deg. 16′ W., 12.05 m. to point 4;\n\nthence N. 68 deg. 00′ E., 24.01 m. to point 5;\n\nthence S. 23 deg. 16′ E., 6.50 m. to point 6;\n\nthence N. 69 deg. 58′ E., 31.10 m. to point 7;\n\nthence S. 22 deg. 32′ E., 56.05 m. to point 8;\n\nthence N. 75 deg. 36′ E., 8.00 m. to point 9;\n\nthence S. 12 deg. 45′ E., 30.00 m. to point 10;\n\nthence N. 69 deg. 10′ W., 25.00 m. to point 11;\n\nthence N. 9 deg. 07′ E., 8.50 m. to point 12;\n\nthence S. 89 deg. 00′ W., 39.00 m. to the point\n\nof beginning; containing an area of THREE THOUSAND TWO HUNDRED SEVENTY ONE (3,271) Square Meters. All points referred to are indicated on the plan and marked on the ground by Old Points; bearings true.\n\nNOTE: This is a portion of Lot 1, Swo-18580.\n\nIN WITNESS WHEREOF, I have hereunto set my hand and caused the seal of the Republic of the Philippines to be affixed.\n\nDone in the City of Manila, this 27th day of May, in the year of Our Lord, nineteen hundred and sixty-seven.\n\n(SGD.) FERDINAND E. MARCOS President of the Philippines\n\nBy the President: (SGD.) RAFAEL M. SALAS Executive Secretary\n\nSource : CDAsia",
  "word_count": 419,
  "has_html_content": true,
  "is_pdf_only": false,
  "scrape_status": "success",
  "scrape_error": null,
  "scraped_at": "2026-02-23T14:29:54.265307Z"
}