{
  "doc_id": "proclamation-no-855-s-1992",
  "category": "proclamation",
  "category_slug": "proclamations",
  "president_slug": "corazon-c-aquino",
  "date": "1992-01-31",
  "title": "Proclamation No. 855, s. 1992",
  "content_url": "https://www.officialgazette.gov.ph/1992/01/31/proclamation-no-855-s-1992/",
  "pdf_url": "https://www.officialgazette.gov.ph/downloads/1992/01jan/19920131-PROC-0855-CCA.pdf",
  "text": "MALACAÑANG MANILA\n\nPROCLAMATION NO. 855\n\nPROCLAIMING THE ADOPTION AND IMPLEMENTATION OF THE PHILIPPINE PROGRAM OF ACTION FOR CHILDREN IN THE 1990s.\n\nWHEREAS, The World Summit for Children held on 30 September at the UN Headquarters in New York adopted the World Declaration on the Survival, Protection and Development of Children in the 1990s;\n\nWHEREAS, The Philippines is a signatory to the World Declaration on the Survival, Protection and Development of Children in the 1990s in support of the Convention on the Rights of the Child which was adopted by the UN General Assembly on 20 November 1989, with the force of international law by 2 September 1990;\n\nWHEREAS, The Philippines is committed to prepare a National Plan for Children, 1991-2000, which will serve as the basis for the government’s report on the progress of implementation to the United Nations before September 1992, two years after the entry into force of the Treaty for the Philippines, and every five years thereafter;\n\nWHEREAS, The Philippine Program of Action for children in the 1990s is a continuation of the National Plan for Children (1990-1992) and is consistent with among others, the Medium Term Philippine Development Plan, the Education for All, Philippine Plan for Action (1991-2000), the Philippine Food and Nutrition Plan, the Water Supply, Sewerage and Sanitation Master Plan (1988-2000) and Health for All by the Year 2000;\n\nWHEREAS, The Program of Action for Children has been reviewed and approved by the Council for the Welfare of Children Board and the Social Development Committee, both Technical Board and Cabinet Level;\n\nNOW, THEREFORE, I, CORAZON C. AQUINO, President of the Republic of the Philippines, by virtue of the powers vested in me by the law, do hereby proclaim the adoption and implementation of the Philippine Plan of Action for Children in the 1990s entitled: “The Filipino Children: 2000 and Beyond”.\n\nI hereby call upon the Council for the Welfare of Children to undertake the operationalization of the coordinative task through its National as well as the Regional, Provincial/City, Municipal, and Barangay mechanisms through the integration of the plan in the overall plan of the local government units as appropriate.\n\nI hereby direct the following agencies to support and/or implement programs, projects and activities for the survival, protection and development of children in the 1990s in active collaboration with the local government units:\n\na. Department of Social Welfare and Development;\n\nb. Department of Education, Culture and Sports;\n\nc. Department of Health;\n\nd. Department of Labor and Employment;\n\ne. Department of Agriculture;\n\nf. Department of Justice;\n\ng. Department of the Interior and Local Government;\n\nh. National Economic and Development Authority;\n\ni. National Nutrition Council;\n\nj. Non-Government Organizations (licensed and accredited by the government agency-members of the Council for the Welfare of Children as provided by law)\n\nIN WITNESS THEREFORE, I have hereunto set my hand and caused the seal of the Republic of the Philippines to be affixed.\n\nDONE in the City of Manila, this 31st day of January, in the year of Our Lord, nineteen hundred and ninety-two.\n\n(Sgd.) CORAZON C. AQUINO President of the Philippines\n\nBy the President: (Sgd.) FRANKLIN M. DRILON Executive Secretary\n\nSource: CDAsia",
  "word_count": 522,
  "has_html_content": true,
  "is_pdf_only": false,
  "scrape_status": "success",
  "scrape_error": null,
  "scraped_at": "2026-02-23T13:59:15.815113Z"
}