{
  "doc_id": "executive-order-no-375-s-1950",
  "category": "executive_order",
  "category_slug": "executive-orders",
  "president_slug": "elpidio-quirino",
  "date": "1950-11-27",
  "title": "Executive Order No. 375, s. 1950",
  "content_url": "https://www.officialgazette.gov.ph/1950/11/27/executive-order-no-375-s-1950/",
  "pdf_url": "https://www.officialgazette.gov.ph/downloads/1950/11nov/19501127-EO-0375-EQ.pdf",
  "text": "MALACAÑANG MANILA\n\nEXECUTIVE ORDER NO. 375\n\nORGANIZING A PORTION OF THE MUNICIPALITY OF BALER, PROVINCE OF QUEZON, INTO AN INDEPENDENT MUNICIPALITY UNDER THE NAME OF DIPACULAO\n\nUpon the recommendation of the Secretary of the Interior and pursuant to the provisions of section 68 of the Revised Administrative Code, there is hereby created in the Province of Quezon a municipality under the name of Dipaculao, comprising the northern portion of Baler, more particularly described and bounded as follows:\n\nOn the north, by the Quezon-Nueva Vizcaya boundary; on the northeast, by the present Baler-Casiguran boundary; on the east, by the boundary line which the municipality of Dipaculao shall have pursuant to the provisions of section 2321 of the Revised Administrative Code, and on the southwest, by the northeastern boundary of Maria Aurora and northern boundary of Baler. (Reference used in this descriptions: Map of Baler showing the proposed political boundaries of proposed municipality of Dipaculao, scale 1:20,000, prepared in the Bureau of Public Works, Lucena, Quezon.)\n\nThe municipality of Dipaculao, as herein organized, shall have the following barrios: Dipaculao, which shall be the seat of the municipal government, Mijares, Ipil, Salay, Bayabas, Mukdol, Buenavista, Diarabasin, Dibutunan, Balongan, Mabiiao-bilao, Dinadiawan, Diamanan, Puange, Lubbot, Toytoyan and Gupa.\n\nThe municipality of Baler shall have its present territory minus the portion thereof included in the municipality of Dipaculao.\n\nThe municipality of Dipaculao shall begin to exist upon the appointment and qualification of the mayor, vice-mayor and a majority of the councilors.\n\nDone in the City of Manila, this 27th day of November, in the year of Our Lord, nineteen hundred and fifty, and of the Independence of the Philippines, the fifth.\n\n(Sgd.) ELPIDIO QUIRINO President of the Philippines\n\nBy the President:\n\n(Sgd.) TEODORO EVANGELISTA Executive Secretary\n\nSource : Presidential Museum and Library\n\nQuirino, E. (1950). Executive Order No. 375 : Organizing a portion of the municipality of Baler, province of Quezon, into an independent municipality under the name of Dipaculao. Official Gazette of the Republic of the Philippines, 46 (11), 5329.",
  "word_count": 335,
  "has_html_content": true,
  "is_pdf_only": false,
  "scrape_status": "success",
  "scrape_error": null,
  "scraped_at": "2026-02-23T05:55:22.249828Z"
}