{
  "doc_id": "executive-order-no-245-s-1949",
  "category": "executive_order",
  "category_slug": "executive-orders",
  "president_slug": "elpidio-quirino",
  "date": "1949-07-20",
  "title": "Executive Order No. 245, s. 1949",
  "content_url": "https://www.officialgazette.gov.ph/1949/07/20/executive-order-no-245-s-1949/",
  "pdf_url": "https://www.officialgazette.gov.ph/downloads/1949/07jul/19490720-EO-0245-EQ.pdf",
  "text": "MALACAÑANG MANILA\n\nEXECUTIVE ORDER NO. 245\n\nORGANIZING A PORTION OF THE MUNICIPALITY OF PAGADIAN, PROVINCE OF ZAMBOANGA, INTO AN INDEPENDENT MUNICIPALITY UNDER THE NAME OF LABANGAN.\n\nUpon the recommendation of the Secretary of the Interior, and pursuant to the provisions of section 68 of the Revised Administrative Code, the barrios of Labangan, Tacuran, Binayan, Bokong and Lantian, and the sitios of Sambulawan, Backay Dacu, Luya, Bulanit, Militar, Tagulo, Tonotungan, Tabuan and Bagolupa, all of the municipality of Pagadian, Zamboanga, are hereby segregated from the said municipality, and organized into an independent municipality under the name of Labangan, with the seat of government at Barrio Labangan.\n\nThe municipality of Pagadian shall have its present territory, minus the portion thereof comprised in the municipality of Labangan.\n\nThe municipality of Labangan, as herein organized, shall begin to exist upon the appointment and qualification of the mayor, the vice-mayor, and a majority of the councilors thereof.\n\nDone in the City of Manila, this 20th day of July, in the year of Our Lord, nineteen hundred and forty-nine, and of the Independence of the Philippines, the fourth.\n\n(Sgd.) ELPIDIO QUIRINO President of the Philippines\n\nBy the President:\n\n(Sgd.) TEODORO EVANGELISTA Executive Secretary\n\nSource: Presidential Museum and Library\n\nQuirino, E. (1949). Executive Order No. 245 : Organizing a portion of the Municipality of Pagadian, Province of Zamboanga, into an independent municipality under the name of Labangan. Official Gazette of the Republic of the Philippines, 45 (7), 2742.",
  "word_count": 241,
  "has_html_content": true,
  "is_pdf_only": false,
  "scrape_status": "success",
  "scrape_error": null,
  "scraped_at": "2026-02-23T05:50:07.259567Z"
}