{
  "doc_id": "administrative-order-no-405-s-1977",
  "category": "administrative_order",
  "category_slug": "administrative-orders",
  "president_slug": "ferdinand-e-marcos",
  "date": "1977-04-01",
  "title": "Administrative Order No. 405, s. 1977",
  "content_url": "https://www.officialgazette.gov.ph/1977/04/01/administrative-order-no-405-s-1977/",
  "pdf_url": "https://www.officialgazette.gov.ph/downloads/1977/04apr/19770401-AO-0405-FM.pdf",
  "text": "MALACAÑANG BY THE PRESIDENT OF THE PHILIPPINES\n\nADMINISTRATIVE ORDER NO. 405\n\nORDERING THE REINSTATEMENT WITH PROPER PENALTY OF EIGHTY-NINE (89) OFFICIALS AND EMPLOYEES OF THE DEPARTMENT OF AGRICULTURE DISMISSED FROM THE SERVICE ON SEPTEMBER 19, 1975\n\nWHEREAS, on September 19, 1975, some 2,000 officials and employees in the government were ordered separated from the service;\n\nWHEREAS, errors were committed in the assessment and evaluation of some of the cases of said officials and employees;\n\nWHEREAS, to correct such errors, Administrative Order No. 370 dated October 24, 1975 was issued, creating a Committee to take cognizance of petitions for reconsiderations of dismissed officials and employees and to conduct a. review of all the cases of these officials and employees;\n\nWHEREAS, upon a careful review of the cases of the dismissed officials and employees and an evaluation of the evidence in support of their dismissal, the Committee found that a number of officials and employees in the Department of Agriculture deserve to be meted out penalties leas than outright dismissal.\n\nNOW, THEREFORE. I, FERDINAND E. MARCOS, President of the Philippines, by virtue of the power vested in me by the Constitution, do hereby order the immediate reinstatement of the following eighty-nine (89) officials and employees of the Department of Agriculture provided, however, that during the period from September 19, 1975 up to the date of their reinstatement in accordance with this Order, these officials and employees shall be considered under suspension without pay:\n\nA. Department Proper\n\nB. National Food and Agriculture Council\n\nC. Bureau, of Animal Industry\n\nD. Bureau of Agricultural Extension\n\nE. Bureau of Plant Industry\n\nF. Bureau of Soils\n\nDone in the City of Manila, this 1st day of April, in the year of Our Lord, nineteen hundred and seventy-seven.\n\n(Sgd.) FERDINAND E. MARCOS President of the Philippines\n\nBy the President:\n\n(Sgd.) JACOBO C. CLAVE Presidential Executive Assistant\n\nSource: Malacañang Records Office\n\nOffice of the President of the Philippines. (1977). [Administrative Order Nos. : 349 – 438]. Manila : Malacañang Records Office.",
  "word_count": 332,
  "has_html_content": true,
  "is_pdf_only": false,
  "scrape_status": "success",
  "scrape_error": null,
  "scraped_at": "2026-02-23T03:43:15.279185Z"
}