{
  "doc_id": "proclamation-no-728-s-1941",
  "category": "proclamation",
  "category_slug": "proclamations",
  "president_slug": "manuel-l-quezon",
  "date": "1941-06-24",
  "title": "Proclamation No. 728, s. 1941",
  "content_url": "https://www.officialgazette.gov.ph/1941/06/24/proclamation-no-728-s-1941/",
  "pdf_url": "https://www.officialgazette.gov.ph/downloads/1941/06jun/19410624-PROC-0728-MLQ.pdf",
  "text": "PROCLAMATION’ NO. 728\n\nRESERVING FOR SCHOOL PURPOSES TWO PARCELS OF THE PUBLIC DOMAIN SITUATED IN THE BARRIO OF TAYABO, MUNICIPALITY OF SAN JOSE, PROVINCE OF NUEVA ECIJA, ISLAND OF LUZON.\n\nUpon the recommendation of the Secretary of Agriculture and Commerce and pursuant to the provisions of section eighty-three of Commonwealth Act Numbered One hundred and forty-one, as amended, I hereby withdraw from sale or settlement and reserve for school purposes, under the administration of the Director of Education, subject to private rights, if any there be, the following parcels of the public domain, situated in the barrio of Tayabo, municipality of San Jose, Province of Nueva Ecija, Island of Luzon, and particularly described in Bureau of Lands plan Mr-489, to wit:\n\nLot No. 1, Mr-489. — Beginning at a point marked 1 on Bureau of Lands plan Mr-489, N. 31° 28′ W. 1,155.37 m., more or less, from B. B^ M. No. 36 ; , San Jose cadastre No. 66, thence S. 29°! 46′ E. 77.63 m. to point 2; S. 77° 26′ W. 23.64 m. to point 3; S. 15° 52′ E. 32.11 m. to point 4; S. 71° 05′ W. 70.96 m. to point 5; N. 31° 29′ W. 34.90 m. to point 6; N. 20° 27′ W. 81.60 m. to point 7; N. 77° 17′ E. 91.86 m. to point 1, point of beginning.\n\nContaining an area of ten thousand fifty-two (10,052) square meters, more or less.\n\nAll corners are B. L. concrete monuments.\n\nBounded on the northeast by provincial road and public land; on the southeast, by public land; on the southwest, by lot No. 2 and public land; and on the northwest, by public land.\n\nLot No. 2, Mr-4-89. —Beginning at a point marked 1 on Bureau of Lands plan Mr-489, N. 36° 46′ W. 1,109.46 m., more or less, from B. B. M. No. 36, San Jose cadastre No. 66, thence S. 31° 29′ E- 34.90.m. to point 2; S. 71° 15′ W-28.68 m. to point 3; N. 21° 23′ W. 35.00 m. to point 4; N. 73° 35′ E. 22.61 m. to point 1, point of beginning.\n\nContaining an area of eight hundred eighty-two (882) square meters, more or less.\n\nAll corners are B. L. concrete monuments.\n\nBounded on the northeast by lot No. 1; on the southeast, by public land; on the southwest, by lot No. 2996; and on the northwest, by public land.\n\nBearings true. Declination, 0° 42′ E.\n\nPoints referred to are marked on Bureau of Lands plan Mr-489.\n\nSurveyed: July 1, 1940.\n\nApproved: February 27, 1941.\n\nNOTE.—Lot No. 1 = Lot No. 4442, portions of lot No. 1125 of San Jose cadastre No. 66, case No. 2.\n\nLot No. 2 = Lot No. 4443, portion of lot No. 1125 of San: Jose cadastre No. 66, case No. 2.\n\nLot No. 1125 was declared public land on May 17, 1925.\n\nIn witness whereof, I have hereunto set my hand and caused the seal of the Commonwealth of the Philippines to be affixed.\n\nDone at the City of Manila, this twenty-fourth day of June, in the year of Our Lord, nineteen hundred and forty-one, and of the Commonwealth of the Philippines, the sixth.\n\nMANUEL L. QUEZON President of the Philippines\n\nBy the President: JORGE B. VARGAS Secretary to the President\n\nSource: University of the Philippines, College of Law Library",
  "word_count": 558,
  "has_html_content": true,
  "is_pdf_only": false,
  "scrape_status": "success",
  "scrape_error": null,
  "scraped_at": "2026-02-23T17:50:13.036715Z"
}