{
  "doc_id": "proclamation-no-586-s-1959",
  "category": "proclamation",
  "category_slug": "proclamations",
  "president_slug": "carlos-p-garcia",
  "date": "1959-05-15",
  "title": "Proclamation No. 586, s. 1959",
  "content_url": "https://www.officialgazette.gov.ph/1959/05/15/proclamation-no-586-s-1959/",
  "pdf_url": "https://www.officialgazette.gov.ph/downloads/1959/05may/19590515-PROC-0586-CPG.pdf",
  "text": "MALACAÑANG\n\nRESIDENCE OF THE PRESIDENT OF THE PHILIPPINES MANILA\n\nPROCLAMATION NO. 586\n\nDESIGNATING THE PERIOD FROM JUNE 1 TO JULY 15, 1959, FOR THE ELEVENTH ANNUAL FUND CAMPAIGN OF THE COMMUNITY CHEST OF GREATER MANILA\n\nTo enable the Community Chest of Greater Manila to carry on its community welfare services, I, Carlos P. Garcia, President of the Philippines, do hereby designate the period from June 1 to July 15, 1959, for its eleventh annual fund campaign.\n\nI call upon all residents, firms, and organizations in the City of Manila, Quezon City, Pasay City, and the municipalities of Caloocan, Makati, Malabon, Mandaluyong, Navotas, Parañaque, and San Juan to support this campaign and to give generously to the Community Chest of Greater Manila which unites into one annual appeal the fund campaigns of the following:\n\nI authorize all government officials and employees, including school authorities and teachers, to accept, for the Community Chest of Greater Manila, fund-raising responsibilities and to give it active support and leadership in their respective communities.\n\nIN WITNESS WHEREOF, I have hereunto set my hand and caused the seal of the Republic of the Philippines to be affixed.\n\nDone in the City of Manila, this 15th day of May, in the year of Our Lord, nineteen hundred and fifty-nine, and of the Independence of the Philippines, the thirteenth.\n\nCARLOS P. GARCIA President of the Philippines\n\nBy the President:\n\nJUAN C. PAJO Executive Secretary\n\nSource: University of the Philippines, College of Law Library",
  "word_count": 244,
  "has_html_content": true,
  "is_pdf_only": false,
  "scrape_status": "success",
  "scrape_error": null,
  "scraped_at": "2026-02-23T13:30:32.170714Z"
}