{
  "doc_id": "proclamation-no-407-s-1957",
  "category": "proclamation",
  "category_slug": "proclamations",
  "president_slug": "carlos-p-garcia",
  "date": "1957-04-11",
  "title": "Proclamation No. 407, s. 1957",
  "content_url": "https://www.officialgazette.gov.ph/1957/04/11/proclamation-no-407-s-1957/",
  "pdf_url": "https://www.officialgazette.gov.ph/downloads/1957/04apr/19570411-PROC-0407-CPG.pdf",
  "text": "MALACAÑANG\n\nRESIDENCE OF THE PRESIDENT OF THE PHILIPPINES MANILA\n\nPROCLAMATION NO. 407\n\nREVOKING PROCLAMATION NO. 208, SERIES OF 1929, WHICH ESTABLISHED THE BATAN ISLAND FOREST RESERVE AND DECLARING THE AREAS EMBRACED THEREUNDER OPEN TO DISPOSITION UNDER THE PROVISIONS OF THE MINING ACT\n\nWHEREAS, a petition has been filed for the release of the areas covered by Proclamation No. 208, series of 1929, which established the Batan Island Forest Reserve;\n\nWHEREAS, the findings of the Director of Mines show that the area sought to be released from the Batan Island Forest Reserve appears to be highly mineralized;\n\nWHEREAS, under the provisions of section fourteen of Commonwealth Act Numbered One hundred and thirty-seven, as amended, otherwise known as the Mining Act, lands within reservations for purposes other than mining, which, after such reservation is made, are found to be more valuable for their mineral contents than for the purposes for which the reservation was made, may be withdrawn from such reservation by the President with the concurrence of the Congress of the Philippines.\n\nNOW, THEREFORE, upon the recommendation of the Secretary of Agriculture and Natural Resources and pursuant to the provisions of section fourteen of Common-wealth Act Numbered One hundred and thirty-seven, as amended, otherwise known as the Mining Act, I hereby revoke Proclamation No. 208, dated January 12, 1929, and declare the area embraced thereunder open to disposition under the provisions of the Mining Act, provided, that the cutting, removal, and utilization of timber and other forest products therefrom shall be made in accordance with the provisions of the existing Forest and Internal Revenue Laws and Regulations.\n\nThis proclamation shall take effect only upon the concurrence of the Congress of the Philippines.\n\nIN WITNESS WHEREOF, I have hereunto set my hand and caused the seal of the Republic of the Philippines to be affixed.\n\nDone in the City of Manila, this 11th day of April, in the year of Our Lord, nineteen hundred and fifty-seven, and of the Independence of the Philippines, the eleventh.\n\nCARLOS P. GARCIA President of the Philippines\n\nBy the President:\n\nFORTUNATO DE LEON Executive Secretary\n\nSource: University of the Philippines, College of Law Library",
  "word_count": 357,
  "has_html_content": true,
  "is_pdf_only": false,
  "scrape_status": "success",
  "scrape_error": null,
  "scraped_at": "2026-02-23T13:25:54.446660Z"
}