{
  "doc_id": "proclamation-no-105-s-1948",
  "category": "proclamation",
  "category_slug": "proclamations",
  "president_slug": "elpidio-quirino",
  "date": "1948-11-19",
  "title": "Proclamation No. 105, s. 1948",
  "content_url": "https://www.officialgazette.gov.ph/1948/11/19/proclamation-no-105-s-1948/",
  "pdf_url": "https://www.officialgazette.gov.ph/downloads/1948/11nov/19481119-PROC-0105-EQ.pdf",
  "text": "MALACAÑAN PALACE MANILA\n\nPROCLAMATION NO. 105\n\nDECLARING THE PERIOD FROM DECEMBER 12 TO 18, 1948, AS AVIATION WEEK\n\nWHEREAS, aviation plays an important role in promoting the progress and insuring the security of the nation; and\n\nWHEREAS, it is desirable that a widespread interest in aviation be aroused among our people;\n\nNOW, THEREFORE, I, Eipidio Quirino President of the Philippines, by virtue of the powers vested in me by law, do hereby designate the period from December 12 to 18, 1948, as Aviation Week, and enjoin all government officials and employees and all citizens of j the Philippines to lend their full cooperation in the observance of this week.\n\nIN WITNESS WHEREOF, I have hereunto set my hand and caused the seal of the Republic of the Philippines to be affixed.\n\nDone in the City of Manila, this 19th day of November, in the year of Our Lord, nineteen hundred and forty-eight, and of the Independence of the Philippines, the third.\n\nELPIDIO QUIRINO President of the Philippines\n\nBy the President:\n\nTEODORO EVANGELISTA Executive Secretary\n\nSource: University of the Philippines, College of Law Library",
  "word_count": 183,
  "has_html_content": true,
  "is_pdf_only": false,
  "scrape_status": "success",
  "scrape_error": null,
  "scraped_at": "2026-02-23T14:15:32.067335Z"
}