{
  "doc_id": "presidential-decree-no-1826-s-1981",
  "category": "presidential_decree",
  "category_slug": "presidential-decrees-executive-issuances",
  "president_slug": "ferdinand-e-marcos",
  "date": "1981-01-16",
  "title": "Presidential Decree No. 1826, s. 1981",
  "content_url": "https://www.officialgazette.gov.ph/1981/01/16/presidential-decree-no-1826-s-1981/",
  "pdf_url": "https://www.officialgazette.gov.ph/downloads/1981/16jan/19810116-PD-1826-FM.pdf",
  "text": "MALACAÑANG Manila\n\nPRESIDENTIAL DECREE No. 1826\n\nAN ACT AMENDING SECTION 6 OF PRESIDENTIAL DECREE NO. 1630, TO BE KNOWN AS “TANODBAYAN”\n\nWHEREAS, Republic Act No. 3595 amending RA 1568 provides a special retirement scheme for the Auditor General and the Chairman and Members of the Commission on Elections and P.D. 1582 extended the same retirement benefits to the Chairman and Members of the Civil Service Commission;\n\nWHEREAS, the Sandiganbayan considered to be under the judiciary, is covered by the special retirement law for justices and judges;\n\nWHEREAS, the Tanodbayan Decree, P.D. 1630, is silent on the retirement benefits granted to the Tanodbayan and his Deputies, thereby leaving them as the only heads of a constitutional body without a special retirement plan;\n\nNOW, THEREFORE, I, FERDINAND E. MARCOS, President of the Philippines, by virtue of the power vested in me by the Constitution, do hereby order and decree that Sec. 6 of P.D. 1630 be revised to read as follows:\n\nSection 6. Term of Office and Retirement Benefits.\n\n(a) The Tanodbayan and his Deputies shall serve for a term of seven years without reappointment unless removed by the President upon his determination that the Tanodbayan or any of his Deputies has become incapacitated or has been guilty of neglect of duty, or misconduct;\n\n(b) THE TANODBAYAN AND HIS DEPUTIES ARE GRANTED THE SAME RETIREMENT AND RELATED BENEFITS AS NOW EXTENDED AND MAY SUBSEQUENTLY BE GRANTED TO THE CHAIRMAN AND MEMBERS OF THE COMMISSION ON AUDIT, THE COMMISSION ON ELECTIONS AND THE CIVIL SERVICE COMMISSION.\n\n(c) If the Office of the Tanodbayan becomes vacant for any cause, the Senior Deputy Tanodbayan shall serve as Acting Tanodbayan until the Tanodbayan shall have been appointed for a full term.\n\nDone in the City of Manila, this 16th day of January in the year of Our Lord, nineteen hundred and eighty-one.\n\n(Sgd.) FERDINAND E. MARCOS President of the Philippines\n\nBy the President: (Sgd.) JUAN C. TUVERA Presidential Executive Assistant\n\nSource: Malacañang Records Office",
  "word_count": 328,
  "has_html_content": true,
  "is_pdf_only": false,
  "scrape_status": "success",
  "scrape_error": null,
  "scraped_at": "2026-02-23T13:05:56.901390Z"
}