{
  "doc_id": "letter-of-instruction-no-135-a-s-1973",
  "category": "letter_of_instruction",
  "category_slug": "letters-of-instruction",
  "president_slug": "ferdinand-e-marcos",
  "date": "1973-10-11",
  "title": "Letter of Instruction No. 135-A, s. 1973",
  "content_url": "https://www.officialgazette.gov.ph/1973/10/11/letter-of-instruction-no-135-a-s-1973/",
  "pdf_url": "https://www.officialgazette.gov.ph/downloads/1973/10oct/19731011-LOI-0135-A-FM.pdf",
  "text": null,
  "word_count": null,
  "has_html_content": false,
  "is_pdf_only": true,
  "scrape_status": "success",
  "scrape_error": null,
  "scraped_at": "2026-02-23T09:57:28.577468Z"
}
